mcp_uuid_server/__init__.py
mcp_uuid_server/server.py
mcp_uuid_server/uuid_core.py
mcp_uuid_server-0.1.6.dist-info/METADATA
mcp_uuid_server-0.1.6.dist-info/WHEEL
mcp_uuid_server-0.1.6.dist-info/entry_points.txt
mcp_uuid_server-0.1.6.dist-info/licenses/LICENSE
mcp_uuid_server-0.1.6.dist-info/RECORD
