Metadata-Version: 2.4
Name: mcp-uuid-server
Version: 0.1.6
Summary: MCP server for generating UUIDv7 strings.
Project-URL: Homepage, https://github.com/pomazanbohdan/mcp-uuidv7-generator
Project-URL: Bug Tracker, https://github.com/pomazanbohdan/mcp-uuidv7-generator/issues
Author-email: Pomazan Bohdan <pomazan.bogdan@gmail.com>
License-File: LICENSE
Classifier: License :: OSI Approved :: MIT License
Classifier: Operating System :: OS Independent
Classifier: Programming Language :: Python :: 3
Requires-Python: >=3.8
Requires-Dist: uuid6
